[{"esquema": {"esquema_id": 1, "nome": "3-4-3", "posicoes": {"ata": 3, "gol": 1, "lat": 0, "mei": 4, "tec": 1, "zag": 3}}, "jogadores": [{"apelido": "Sorriso", "atleta_id": 111333, "capitao": true, "clube_id": 286, "entrou_em_campo": true, "foto": "https://s.glbimg.com/es/sde/f/2021/03/25/5f6996b15f5e77bade868f8e343a077f_FORMATO.png", "media": 2.99, "pontos": 17.3, "pontuacao": 17.3, "posicao_id": 5, "preco": 7.36, "preco_anterior": 6.01, "rodada_id": 28, "scout": {"DS": 5, "FC": 1, "FD": 5, "FF": 4, "FS": 8, "PI": 4}, "variacao": 1.35}, {"apelido": "John Kennedy", "atleta_id": 110759, "capitao": false, "clube_id": 266, "entrou_em_campo": true, "foto": "https://s.glbimg.com/es/sde/f/2021/08/19/b1b9b8fc3e7ba9cdea447bad10b25ded_FORMATO.png", "media": 2.29, "pontos": 15.6, "pontuacao": 15.6, "posicao_id": 5, "preco": 5.47, "preco_anterior": 2.7399999999999998, "rodada_id": 28, "scout": {"CA": 1, "DS": 2, "FC": 3, "FD": 1, "FS": 2, "G": 2, "I": 1, "PI": 6}, "variacao": 2.73}, {"apelido": "Ademir", "atleta_id": 101314, "capitao": false, "clube_id": 327, "entrou_em_campo": true, "foto": "https://s.glbimg.com/es/sde/f/2021/06/04/efcfc5345f6f86f495de23422e316d01_FORMATO.jpeg", "media": 4.82, "pontos": 12.1, "pontuacao": 12.1, "posicao_id": 5, "preco": 9.27, "preco_anterior": 7.52, "rodada_id": 28, "scout": {"DS": 2, "FF": 2, "FS": 1, "G": 1, "PI": 10, "PS": 1}, "variacao": 1.75}, {"apelido": "Maílson", "atleta_id": 98034, "capitao": false, "clube_id": 292, "entrou_em_campo": true, "foto": "https://s.glbimg.com/es/sde/f/2021/04/27/978af8903185f1406809c274d6c681f5_FORMATO.png", "media": 5.09, "pontos": 12.5, "pontuacao": 12.5, "posicao_id": 1, "preco": 10.3, "preco_anterior": 9.270000000000001, "rodada_id": 28, "scout": {"DE": 14, "FS": 1, "GS": 2}, "variacao": 1.03}, {"apelido": "Lucas Lima", "atleta_id": 80583, "capitao": false, "clube_id": 356, "entrou_em_campo": true, "foto": "https://s.glbimg.com/es/sde/f/2021/08/30/940ccef3e9a32ebab051e4e097fc4ec3_FORMATO.png", "media": 1.87, "pontos": 16.1, "pontuacao": 16.1, "posicao_id": 4, "preco": 6.35, "preco_anterior": 3.6799999999999997, "rodada_id": 28, "scout": {"A": 1, "DS": 1, "FC": 1, "FD": 1, "FF": 3, "G": 1, "PI": 10}, "variacao": 2.67}, {"apelido": "Alê", "atleta_id": 86388, "capitao": false, "clube_id": 327, "entrou_em_campo": true, "foto": "https://s.glbimg.com/es/sde/f/2021/06/04/fb4e69d36e6a93b5e9f5c927e3d29f8c_FORMATO.png", "media": 3.21, "pontos": 14.3, "pontuacao": 14.3, "posicao_id": 4, "preco": 7.17, "preco_anterior": 5.15, "rodada_id": 28, "scout": {"DS": 7, "FC": 2, "FS": 1, "G": 1, "PI": 2}, "variacao": 2.02}, {"apelido": "Gustavo Scarpa", "atleta_id": 87999, "capitao": false, "clube_id": 275, "entrou_em_campo": true, "foto": "https://s.glbimg.com/es/sde/f/2021/04/30/e594285e6781941b0f08b58d66d6669e_FORMATO.png", "media": 4.56, "pontos": 13.5, "pontuacao": 13.5, "posicao_id": 4, "preco": 14.84, "preco_anterior": 12.71, "rodada_id": 28, "scout": {"A": 1, "DS": 2, "FD": 3, "FF": 3, "FS": 3, "PI": 10}, "variacao": 2.13}, {"apelido": "Felipe Melo", "atleta_id": 38545, "capitao": false, "clube_id": 275, "entrou_em_campo": true, "foto": "https://s.glbimg.com/es/sde/f/2021/04/30/6eeb5a32e1114760b24bf4689330fb43_FORMATO.png", "media": 1.06, "pontos": 11.8, "pontuacao": 11.8, "posicao_id": 4, "preco": 6.36, "preco_anterior": 3.7700000000000005, "rodada_id": 28, "scout": {"DS": 3, "FC": 2, "FF": 2, "FS": 1, "G": 1, "PI": 3}, "variacao": 2.59}, {"apelido": "Guto Ferreira", "atleta_id": 37245, "capitao": false, "clube_id": 265, "entrou_em_campo": true, "foto": "https://s.glbimg.com/es/sde/f/2021/04/27/7b5d614f3eafc2e2e12922930cd3590e_FORMATO.png", "media": 3.94, "pontos": 7.73, "pontuacao": 7.73, "posicao_id": 6, "preco": 9.99, "preco_anterior": 9.4, "rodada_id": 28, "scout": null, "variacao": 0.59}, {"apelido": "Luiz Otávio ", "atleta_id": 86863, "capitao": false, "clube_id": 265, "entrou_em_campo": true, "foto": "https://s.glbimg.com/es/sde/f/2021/03/26/0e2a57894c04137ce7e329cbe588f1c2_FORMATO.png", "media": 2.92, "pontos": 13.8, "pontuacao": 13.8, "posicao_id": 3, "preco": 6.89, "preco_anterior": 5.2299999999999995, "rodada_id": 28, "scout": {"DS": 1, "G": 1, "PI": 2, "SG": 1}, "variacao": 1.66}, {"apelido": "Éder", "atleta_id": 91203, "capitao": false, "clube_id": 373, "entrou_em_campo": true, "foto": "https://s.glbimg.com/es/sde/f/2021/05/02/0302eafbbfe7b451db5ddf34a1c4bfaf_FORMATO.png", "media": 1.88, "pontos": 10.5, "pontuacao": 10.5, "posicao_id": 3, "preco": 9.07, "preco_anterior": 7.5200000000000005, "rodada_id": 28, "scout": {"A": 1, "FC": 1, "FF": 1, "FS": 1, "PI": 3, "SG": 1}, "variacao": 1.55}, {"apelido": "Titi", "atleta_id": 50353, "capitao": false, "clube_id": 356, "entrou_em_campo": true, "foto": "https://s.glbimg.com/es/sde/f/2021/04/27/f556d6eae390e4f92eed5cf6ec49c085_FORMATO.png", "media": 3.69, "pontos": 8.1, "pontuacao": 8.1, "posicao_id": 3, "preco": 10.05, "preco_anterior": 10.040000000000001, "rodada_id": 28, "scout": {"DS": 3, "FC": 1, "FS": 2, "PI": 4, "SG": 1}, "variacao": 0.01}], "pontuacao": 170.63, "preco": 83.04, "valorizacao": 20.080000000000002}, {"esquema": {"esquema_id": 2, "nome": "3-5-2", "posicoes": {"ata": 2, "gol": 1, "lat": 0, "mei": 5, "tec": 1, "zag": 3}}, "jogadores": [{"apelido": "Sorriso", "atleta_id": 111333, "capitao": true, "clube_id": 286, "entrou_em_campo": true, "foto": "https://s.glbimg.com/es/sde/f/2021/03/25/5f6996b15f5e77bade868f8e343a077f_FORMATO.png", "media": 2.99, "pontos": 17.3, "pontuacao": 17.3, "posicao_id": 5, "preco": 7.36, "preco_anterior": 6.01, "rodada_id": 28, "scout": {"DS": 5, "FC": 1, "FD": 5, "FF": 4, "FS": 8, "PI": 4}, "variacao": 1.35}, {"apelido": "John Kennedy", "atleta_id": 110759, "capitao": false, "clube_id": 266, "entrou_em_campo": true, "foto": "https://s.glbimg.com/es/sde/f/2021/08/19/b1b9b8fc3e7ba9cdea447bad10b25ded_FORMATO.png", "media": 2.29, "pontos": 15.6, "pontuacao": 15.6, "posicao_id": 5, "preco": 5.47, "preco_anterior": 2.7399999999999998, "rodada_id": 28, "scout": {"CA": 1, "DS": 2, "FC": 3, "FD": 1, "FS": 2, "G": 2, "I": 1, "PI": 6}, "variacao": 2.73}, {"apelido": "Maílson", "atleta_id": 98034, "capitao": false, "clube_id": 292, "entrou_em_campo": true, "foto": "https://s.glbimg.com/es/sde/f/2021/04/27/978af8903185f1406809c274d6c681f5_FORMATO.png", "media": 5.09, "pontos": 12.5, "pontuacao": 12.5, "posicao_id": 1, "preco": 10.3, "preco_anterior": 9.270000000000001, "rodada_id": 28, "scout": {"DE": 14, "FS": 1, "GS": 2}, "variacao": 1.03}, {"apelido": "Lucas Lima", "atleta_id": 80583, "capitao": false, "clube_id": 356, "entrou_em_campo": true, "foto": "https://s.glbimg.com/es/sde/f/2021/08/30/940ccef3e9a32ebab051e4e097fc4ec3_FORMATO.png", "media": 1.87, "pontos": 16.1, "pontuacao": 16.1, "posicao_id": 4, "preco": 6.35, "preco_anterior": 3.6799999999999997, "rodada_id": 28, "scout": {"A": 1, "DS": 1, "FC": 1, "FD": 1, "FF": 3, "G": 1, "PI": 10}, "variacao": 2.67}, {"apelido": "Alê", "atleta_id": 86388, "capitao": false, "clube_id": 327, "entrou_em_campo": true, "foto": "https://s.glbimg.com/es/sde/f/2021/06/04/fb4e69d36e6a93b5e9f5c927e3d29f8c_FORMATO.png", "media": 3.21, "pontos": 14.3, "pontuacao": 14.3, "posicao_id": 4, "preco": 7.17, "preco_anterior": 5.15, "rodada_id": 28, "scout": {"DS": 7, "FC": 2, "FS": 1, "G": 1, "PI": 2}, "variacao": 2.02}, {"apelido": "Gustavo Scarpa", "atleta_id": 87999, "capitao": false, "clube_id": 275, "entrou_em_campo": true, "foto": "https://s.glbimg.com/es/sde/f/2021/04/30/e594285e6781941b0f08b58d66d6669e_FORMATO.png", "media": 4.56, "pontos": 13.5, "pontuacao": 13.5, "posicao_id": 4, "preco": 14.84, "preco_anterior": 12.71, "rodada_id": 28, "scout": {"A": 1, "DS": 2, "FD": 3, "FF": 3, "FS": 3, "PI": 10}, "variacao": 2.13}, {"apelido": "Felipe Melo", "atleta_id": 38545, "capitao": false, "clube_id": 275, "entrou_em_campo": true, "foto": "https://s.glbimg.com/es/sde/f/2021/04/30/6eeb5a32e1114760b24bf4689330fb43_FORMATO.png", "media": 1.06, "pontos": 11.8, "pontuacao": 11.8, "posicao_id": 4, "preco": 6.36, "preco_anterior": 3.7700000000000005, "rodada_id": 28, "scout": {"DS": 3, "FC": 2, "FF": 2, "FS": 1, "G": 1, "PI": 3}, "variacao": 2.59}, {"apelido": "Jair", "atleta_id": 81091, "capitao": false, "clube_id": 282, "entrou_em_campo": true, "foto": "https://s.glbimg.com/es/sde/f/2021/05/02/9f45c3d8021bc336ee9149455cd40768_FORMATO.png", "media": 2.84, "pontos": 11.8, "pontuacao": 11.8, "posicao_id": 4, "preco": 8.88, "preco_anterior": 7.300000000000001, "rodada_id": 28, "scout": {"DS": 4, "FC": 1, "FS": 1, "G": 1, "PI": 2}, "variacao": 1.58}, {"apelido": "Guto Ferreira", "atleta_id": 37245, "capitao": false, "clube_id": 265, "entrou_em_campo": true, "foto": "https://s.glbimg.com/es/sde/f/2021/04/27/7b5d614f3eafc2e2e12922930cd3590e_FORMATO.png", "media": 3.94, "pontos": 7.73, "pontuacao": 7.73, "posicao_id": 6, "preco": 9.99, "preco_anterior": 9.4, "rodada_id": 28, "scout": null, "variacao": 0.59}, {"apelido": "Luiz Otávio ", "atleta_id": 86863, "capitao": false, "clube_id": 265, "entrou_em_campo": true, "foto": "https://s.glbimg.com/es/sde/f/2021/03/26/0e2a57894c04137ce7e329cbe588f1c2_FORMATO.png", "media": 2.92, "pontos": 13.8, "pontuacao": 13.8, "posicao_id": 3, "preco": 6.89, "preco_anterior": 5.2299999999999995, "rodada_id": 28, "scout": {"DS": 1, "G": 1, "PI": 2, "SG": 1}, "variacao": 1.66}, {"apelido": "Éder", "atleta_id": 91203, "capitao": false, "clube_id": 373, "entrou_em_campo": true, "foto": "https://s.glbimg.com/es/sde/f/2021/05/02/0302eafbbfe7b451db5ddf34a1c4bfaf_FORMATO.png", "media": 1.88, "pontos": 10.5, "pontuacao": 10.5, "posicao_id": 3, "preco": 9.07, "preco_anterior": 7.5200000000000005, "rodada_id": 28, "scout": {"A": 1, "FC": 1, "FF": 1, "FS": 1, "PI": 3, "SG": 1}, "variacao": 1.55}, {"apelido": "Titi", "atleta_id": 50353, "capitao": false, "clube_id": 356, "entrou_em_campo": true, "foto": "https://s.glbimg.com/es/sde/f/2021/04/27/f556d6eae390e4f92eed5cf6ec49c085_FORMATO.png", "media": 3.69, "pontos": 8.1, "pontuacao": 8.1, "posicao_id": 3, "preco": 10.05, "preco_anterior": 10.040000000000001, "rodada_id": 28, "scout": {"DS": 3, "FC": 1, "FS": 2, "PI": 4, "SG": 1}, "variacao": 0.01}], "pontuacao": 170.33, "preco": 82.82000000000001, "valorizacao": 19.910000000000004}, {"esquema": {"esquema_id": 3, "nome": "4-3-3", "posicoes": {"ata": 3, "gol": 1, "lat": 2, "mei": 3, "tec": 1, "zag": 2}}, "jogadores": [{"apelido": "Sorriso", "atleta_id": 111333, "capitao": true, "clube_id": 286, "entrou_em_campo": true, "foto": "https://s.glbimg.com/es/sde/f/2021/03/25/5f6996b15f5e77bade868f8e343a077f_FORMATO.png", "media": 2.99, "pontos": 17.3, "pontuacao": 17.3, "posicao_id": 5, "preco": 7.36, "preco_anterior": 6.01, "rodada_id": 28, "scout": {"DS": 5, "FC": 1, "FD": 5, "FF": 4, "FS": 8, "PI": 4}, "variacao": 1.35}, {"apelido": "John Kennedy", "atleta_id": 110759, "capitao": false, "clube_id": 266, "entrou_em_campo": true, "foto": "https://s.glbimg.com/es/sde/f/2021/08/19/b1b9b8fc3e7ba9cdea447bad10b25ded_FORMATO.png", "media": 2.29, "pontos": 15.6, "pontuacao": 15.6, "posicao_id": 5, "preco": 5.47, "preco_anterior": 2.7399999999999998, "rodada_id": 28, "scout": {"CA": 1, "DS": 2, "FC": 3, "FD": 1, "FS": 2, "G": 2, "I": 1, "PI": 6}, "variacao": 2.73}, {"apelido": "Ademir", "atleta_id": 101314, "capitao": false, "clube_id": 327, "entrou_em_campo": true, "foto": "https://s.glbimg.com/es/sde/f/2021/06/04/efcfc5345f6f86f495de23422e316d01_FORMATO.jpeg", "media": 4.82, "pontos": 12.1, "pontuacao": 12.1, "posicao_id": 5, "preco": 9.27, "preco_anterior": 7.52, "rodada_id": 28, "scout": {"DS": 2, "FF": 2, "FS": 1, "G": 1, "PI": 10, "PS": 1}, "variacao": 1.75}, {"apelido": "Maílson", "atleta_id": 98034, "capitao": false, "clube_id": 292, "entrou_em_campo": true, "foto": "https://s.glbimg.com/es/sde/f/2021/04/27/978af8903185f1406809c274d6c681f5_FORMATO.png", "media": 5.09, "pontos": 12.5, "pontuacao": 12.5, "posicao_id": 1, "preco": 10.3, "preco_anterior": 9.270000000000001, "rodada_id": 28, "scout": {"DE": 14, "FS": 1, "GS": 2}, "variacao": 1.03}, {"apelido": "Igor Cariús", "atleta_id": 91639, "capitao": false, "clube_id": 373, "entrou_em_campo": true, "foto": "https://s.glbimg.com/es/sde/f/2021/03/11/e8078fb6e85f647acc4496fbee1d8b18_FORMATO.png", "media": 4.6, "pontos": 17.1, "pontuacao": 17.1, "posicao_id": 2, "preco": 13.61, "preco_anterior": 10.91, "rodada_id": 28, "scout": {"DS": 6, "FC": 3, "FS": 1, "G": 1, "PI": 9, "SG": 1}, "variacao": 2.7}, {"apelido": "Matheus Bahia", "atleta_id": 97899, "capitao": false, "clube_id": 265, "entrou_em_campo": true, "foto": "https://s.glbimg.com/es/sde/f/2021/04/19/52f1b5df1a1d88d986e939213804c1d0_FORMATO.png", "media": 4.98, "pontos": 12.1, "pontuacao": 12.1, "posicao_id": 2, "preco": 12.41, "preco_anterior": 11.33, "rodada_id": 28, "scout": {"A": 1, "DS": 2, "FC": 1, "FF": 1, "FS": 1, "PI": 7, "SG": 1}, "variacao": 1.08}, {"apelido": "Lucas Lima", "atleta_id": 80583, "capitao": false, "clube_id": 356, "entrou_em_campo": true, "foto": "https://s.glbimg.com/es/sde/f/2021/08/30/940ccef3e9a32ebab051e4e097fc4ec3_FORMATO.png", "media": 1.87, "pontos": 16.1, "pontuacao": 16.1, "posicao_id": 4, "preco": 6.35, "preco_anterior": 3.6799999999999997, "rodada_id": 28, "scout": {"A": 1, "DS": 1, "FC": 1, "FD": 1, "FF": 3, "G": 1, "PI": 10}, "variacao": 2.67}, {"apelido": "Alê", "atleta_id": 86388, "capitao": false, "clube_id": 327, "entrou_em_campo": true, "foto": "https://s.glbimg.com/es/sde/f/2021/06/04/fb4e69d36e6a93b5e9f5c927e3d29f8c_FORMATO.png", "media": 3.21, "pontos": 14.3, "pontuacao": 14.3, "posicao_id": 4, "preco": 7.17, "preco_anterior": 5.15, "rodada_id": 28, "scout": {"DS": 7, "FC": 2, "FS": 1, "G": 1, "PI": 2}, "variacao": 2.02}, {"apelido": "Gustavo Scarpa", "atleta_id": 87999, "capitao": false, "clube_id": 275, "entrou_em_campo": true, "foto": "https://s.glbimg.com/es/sde/f/2021/04/30/e594285e6781941b0f08b58d66d6669e_FORMATO.png", "media": 4.56, "pontos": 13.5, "pontuacao": 13.5, "posicao_id": 4, "preco": 14.84, "preco_anterior": 12.71, "rodada_id": 28, "scout": {"A": 1, "DS": 2, "FD": 3, "FF": 3, "FS": 3, "PI": 10}, "variacao": 2.13}, {"apelido": "Guto Ferreira", "atleta_id": 37245, "capitao": false, "clube_id": 265, "entrou_em_campo": true, "foto": "https://s.glbimg.com/es/sde/f/2021/04/27/7b5d614f3eafc2e2e12922930cd3590e_FORMATO.png", "media": 3.94, "pontos": 7.73, "pontuacao": 7.73, "posicao_id": 6, "preco": 9.99, "preco_anterior": 9.4, "rodada_id": 28, "scout": null, "variacao": 0.59}, {"apelido": "Luiz Otávio ", "atleta_id": 86863, "capitao": false, "clube_id": 265, "entrou_em_campo": true, "foto": "https://s.glbimg.com/es/sde/f/2021/03/26/0e2a57894c04137ce7e329cbe588f1c2_FORMATO.png", "media": 2.92, "pontos": 13.8, "pontuacao": 13.8, "posicao_id": 3, "preco": 6.89, "preco_anterior": 5.2299999999999995, "rodada_id": 28, "scout": {"DS": 1, "G": 1, "PI": 2, "SG": 1}, "variacao": 1.66}, {"apelido": "Éder", "atleta_id": 91203, "capitao": false, "clube_id": 373, "entrou_em_campo": true, "foto": "https://s.glbimg.com/es/sde/f/2021/05/02/0302eafbbfe7b451db5ddf34a1c4bfaf_FORMATO.png", "media": 1.88, "pontos": 10.5, "pontuacao": 10.5, "posicao_id": 3, "preco": 9.07, "preco_anterior": 7.5200000000000005, "rodada_id": 28, "scout": {"A": 1, "FC": 1, "FF": 1, "FS": 1, "PI": 3, "SG": 1}, "variacao": 1.55}], "pontuacao": 179.92999999999998, "preco": 91.47, "valorizacao": 21.26}, {"esquema": {"esquema_id": 4, "nome": "4-4-2", "posicoes": {"ata": 2, "gol": 1, "lat": 2, "mei": 4, "tec": 1, "zag": 2}}, "jogadores": [{"apelido": "Sorriso", "atleta_id": 111333, "capitao": true, "clube_id": 286, "entrou_em_campo": true, "foto": "https://s.glbimg.com/es/sde/f/2021/03/25/5f6996b15f5e77bade868f8e343a077f_FORMATO.png", "media": 2.99, "pontos": 17.3, "pontuacao": 17.3, "posicao_id": 5, "preco": 7.36, "preco_anterior": 6.01, "rodada_id": 28, "scout": {"DS": 5, "FC": 1, "FD": 5, "FF": 4, "FS": 8, "PI": 4}, "variacao": 1.35}, {"apelido": "John Kennedy", "atleta_id": 110759, "capitao": false, "clube_id": 266, "entrou_em_campo": true, "foto": "https://s.glbimg.com/es/sde/f/2021/08/19/b1b9b8fc3e7ba9cdea447bad10b25ded_FORMATO.png", "media": 2.29, "pontos": 15.6, "pontuacao": 15.6, "posicao_id": 5, "preco": 5.47, "preco_anterior": 2.7399999999999998, "rodada_id": 28, "scout": {"CA": 1, "DS": 2, "FC": 3, "FD": 1, "FS": 2, "G": 2, "I": 1, "PI": 6}, "variacao": 2.73}, {"apelido": "Maílson", "atleta_id": 98034, "capitao": false, "clube_id": 292, "entrou_em_campo": true, "foto": "https://s.glbimg.com/es/sde/f/2021/04/27/978af8903185f1406809c274d6c681f5_FORMATO.png", "media": 5.09, "pontos": 12.5, "pontuacao": 12.5, "posicao_id": 1, "preco": 10.3, "preco_anterior": 9.270000000000001, "rodada_id": 28, "scout": {"DE": 14, "FS": 1, "GS": 2}, "variacao": 1.03}, {"apelido": "Igor Cariús", "atleta_id": 91639, "capitao": false, "clube_id": 373, "entrou_em_campo": true, "foto": "https://s.glbimg.com/es/sde/f/2021/03/11/e8078fb6e85f647acc4496fbee1d8b18_FORMATO.png", "media": 4.6, "pontos": 17.1, "pontuacao": 17.1, "posicao_id": 2, "preco": 13.61, "preco_anterior": 10.91, "rodada_id": 28, "scout": {"DS": 6, "FC": 3, "FS": 1, "G": 1, "PI": 9, "SG": 1}, "variacao": 2.7}, {"apelido": "Matheus Bahia", "atleta_id": 97899, "capitao": false, "clube_id": 265, "entrou_em_campo": true, "foto": "https://s.glbimg.com/es/sde/f/2021/04/19/52f1b5df1a1d88d986e939213804c1d0_FORMATO.png", "media": 4.98, "pontos": 12.1, "pontuacao": 12.1, "posicao_id": 2, "preco": 12.41, "preco_anterior": 11.33, "rodada_id": 28, "scout": {"A": 1, "DS": 2, "FC": 1, "FF": 1, "FS": 1, "PI": 7, "SG": 1}, "variacao": 1.08}, {"apelido": "Lucas Lima", "atleta_id": 80583, "capitao": false, "clube_id": 356, "entrou_em_campo": true, "foto": "https://s.glbimg.com/es/sde/f/2021/08/30/940ccef3e9a32ebab051e4e097fc4ec3_FORMATO.png", "media": 1.87, "pontos": 16.1, "pontuacao": 16.1, "posicao_id": 4, "preco": 6.35, "preco_anterior": 3.6799999999999997, "rodada_id": 28, "scout": {"A": 1, "DS": 1, "FC": 1, "FD": 1, "FF": 3, "G": 1, "PI": 10}, "variacao": 2.67}, {"apelido": "Alê", "atleta_id": 86388, "capitao": false, "clube_id": 327, "entrou_em_campo": true, "foto": "https://s.glbimg.com/es/sde/f/2021/06/04/fb4e69d36e6a93b5e9f5c927e3d29f8c_FORMATO.png", "media": 3.21, "pontos": 14.3, "pontuacao": 14.3, "posicao_id": 4, "preco": 7.17, "preco_anterior": 5.15, "rodada_id": 28, "scout": {"DS": 7, "FC": 2, "FS": 1, "G": 1, "PI": 2}, "variacao": 2.02}, {"apelido": "Gustavo Scarpa", "atleta_id": 87999, "capitao": false, "clube_id": 275, "entrou_em_campo": true, "foto": "https://s.glbimg.com/es/sde/f/2021/04/30/e594285e6781941b0f08b58d66d6669e_FORMATO.png", "media": 4.56, "pontos": 13.5, "pontuacao": 13.5, "posicao_id": 4, "preco": 14.84, "preco_anterior": 12.71, "rodada_id": 28, "scout": {"A": 1, "DS": 2, "FD": 3, "FF": 3, "FS": 3, "PI": 10}, "variacao": 2.13}, {"apelido": "Felipe Melo", "atleta_id": 38545, "capitao": false, "clube_id": 275, "entrou_em_campo": true, "foto": "https://s.glbimg.com/es/sde/f/2021/04/30/6eeb5a32e1114760b24bf4689330fb43_FORMATO.png", "media": 1.06, "pontos": 11.8, "pontuacao": 11.8, "posicao_id": 4, "preco": 6.36, "preco_anterior": 3.7700000000000005, "rodada_id": 28, "scout": {"DS": 3, "FC": 2, "FF": 2, "FS": 1, "G": 1, "PI": 3}, "variacao": 2.59}, {"apelido": "Guto Ferreira", "atleta_id": 37245, "capitao": false, "clube_id": 265, "entrou_em_campo": true, "foto": "https://s.glbimg.com/es/sde/f/2021/04/27/7b5d614f3eafc2e2e12922930cd3590e_FORMATO.png", "media": 3.94, "pontos": 7.73, "pontuacao": 7.73, "posicao_id": 6, "preco": 9.99, "preco_anterior": 9.4, "rodada_id": 28, "scout": null, "variacao": 0.59}, {"apelido": "Luiz Otávio ", "atleta_id": 86863, "capitao": false, "clube_id": 265, "entrou_em_campo": true, "foto": "https://s.glbimg.com/es/sde/f/2021/03/26/0e2a57894c04137ce7e329cbe588f1c2_FORMATO.png", "media": 2.92, "pontos": 13.8, "pontuacao": 13.8, "posicao_id": 3, "preco": 6.89, "preco_anterior": 5.2299999999999995, "rodada_id": 28, "scout": {"DS": 1, "G": 1, "PI": 2, "SG": 1}, "variacao": 1.66}, {"apelido": "Éder", "atleta_id": 91203, "capitao": false, "clube_id": 373, "entrou_em_campo": true, "foto": "https://s.glbimg.com/es/sde/f/2021/05/02/0302eafbbfe7b451db5ddf34a1c4bfaf_FORMATO.png", "media": 1.88, "pontos": 10.5, "pontuacao": 10.5, "posicao_id": 3, "preco": 9.07, "preco_anterior": 7.5200000000000005, "rodada_id": 28, "scout": {"A": 1, "FC": 1, "FF": 1, "FS": 1, "PI": 3, "SG": 1}, "variacao": 1.55}], "pontuacao": 179.63, "preco": 87.72000000000001, "valorizacao": 22.1}, {"esquema": {"esquema_id": 5, "nome": "4-5-1", "posicoes": {"ata": 1, "gol": 1, "lat": 2, "mei": 5, "tec": 1, "zag": 2}}, "jogadores": [{"apelido": "Sorriso", "atleta_id": 111333, "capitao": true, "clube_id": 286, "entrou_em_campo": true, "foto": "https://s.glbimg.com/es/sde/f/2021/03/25/5f6996b15f5e77bade868f8e343a077f_FORMATO.png", "media": 2.99, "pontos": 17.3, "pontuacao": 17.3, "posicao_id": 5, "preco": 7.36, "preco_anterior": 6.01, "rodada_id": 28, "scout": {"DS": 5, "FC": 1, "FD": 5, "FF": 4, "FS": 8, "PI": 4}, "variacao": 1.35}, {"apelido": "Maílson", "atleta_id": 98034, "capitao": false, "clube_id": 292, "entrou_em_campo": true, "foto": "https://s.glbimg.com/es/sde/f/2021/04/27/978af8903185f1406809c274d6c681f5_FORMATO.png", "media": 5.09, "pontos": 12.5, "pontuacao": 12.5, "posicao_id": 1, "preco": 10.3, "preco_anterior": 9.270000000000001, "rodada_id": 28, "scout": {"DE": 14, "FS": 1, "GS": 2}, "variacao": 1.03}, {"apelido": "Igor Cariús", "atleta_id": 91639, "capitao": false, "clube_id": 373, "entrou_em_campo": true, "foto": "https://s.glbimg.com/es/sde/f/2021/03/11/e8078fb6e85f647acc4496fbee1d8b18_FORMATO.png", "media": 4.6, "pontos": 17.1, "pontuacao": 17.1, "posicao_id": 2, "preco": 13.61, "preco_anterior": 10.91, "rodada_id": 28, "scout": {"DS": 6, "FC": 3, "FS": 1, "G": 1, "PI": 9, "SG": 1}, "variacao": 2.7}, {"apelido": "Matheus Bahia", "atleta_id": 97899, "capitao": false, "clube_id": 265, "entrou_em_campo": true, "foto": "https://s.glbimg.com/es/sde/f/2021/04/19/52f1b5df1a1d88d986e939213804c1d0_FORMATO.png", "media": 4.98, "pontos": 12.1, "pontuacao": 12.1, "posicao_id": 2, "preco": 12.41, "preco_anterior": 11.33, "rodada_id": 28, "scout": {"A": 1, "DS": 2, "FC": 1, "FF": 1, "FS": 1, "PI": 7, "SG": 1}, "variacao": 1.08}, {"apelido": "Lucas Lima", "atleta_id": 80583, "capitao": false, "clube_id": 356, "entrou_em_campo": true, "foto": "https://s.glbimg.com/es/sde/f/2021/08/30/940ccef3e9a32ebab051e4e097fc4ec3_FORMATO.png", "media": 1.87, "pontos": 16.1, "pontuacao": 16.1, "posicao_id": 4, "preco": 6.35, "preco_anterior": 3.6799999999999997, "rodada_id": 28, "scout": {"A": 1, "DS": 1, "FC": 1, "FD": 1, "FF": 3, "G": 1, "PI": 10}, "variacao": 2.67}, {"apelido": "Alê", "atleta_id": 86388, "capitao": false, "clube_id": 327, "entrou_em_campo": true, "foto": "https://s.glbimg.com/es/sde/f/2021/06/04/fb4e69d36e6a93b5e9f5c927e3d29f8c_FORMATO.png", "media": 3.21, "pontos": 14.3, "pontuacao": 14.3, "posicao_id": 4, "preco": 7.17, "preco_anterior": 5.15, "rodada_id": 28, "scout": {"DS": 7, "FC": 2, "FS": 1, "G": 1, "PI": 2}, "variacao": 2.02}, {"apelido": "Gustavo Scarpa", "atleta_id": 87999, "capitao": false, "clube_id": 275, "entrou_em_campo": true, "foto": "https://s.glbimg.com/es/sde/f/2021/04/30/e594285e6781941b0f08b58d66d6669e_FORMATO.png", "media": 4.56, "pontos": 13.5, "pontuacao": 13.5, "posicao_id": 4, "preco": 14.84, "preco_anterior": 12.71, "rodada_id": 28, "scout": {"A": 1, "DS": 2, "FD": 3, "FF": 3, "FS": 3, "PI": 10}, "variacao": 2.13}, {"apelido": "Felipe Melo", "atleta_id": 38545, "capitao": false, "clube_id": 275, "entrou_em_campo": true, "foto": "https://s.glbimg.com/es/sde/f/2021/04/30/6eeb5a32e1114760b24bf4689330fb43_FORMATO.png", "media": 1.06, "pontos": 11.8, "pontuacao": 11.8, "posicao_id": 4, "preco": 6.36, "preco_anterior": 3.7700000000000005, "rodada_id": 28, "scout": {"DS": 3, "FC": 2, "FF": 2, "FS": 1, "G": 1, "PI": 3}, "variacao": 2.59}, {"apelido": "Jair", "atleta_id": 81091, "capitao": false, "clube_id": 282, "entrou_em_campo": true, "foto": "https://s.glbimg.com/es/sde/f/2021/05/02/9f45c3d8021bc336ee9149455cd40768_FORMATO.png", "media": 2.84, "pontos": 11.8, "pontuacao": 11.8, "posicao_id": 4, "preco": 8.88, "preco_anterior": 7.300000000000001, "rodada_id": 28, "scout": {"DS": 4, "FC": 1, "FS": 1, "G": 1, "PI": 2}, "variacao": 1.58}, {"apelido": "Guto Ferreira", "atleta_id": 37245, "capitao": false, "clube_id": 265, "entrou_em_campo": true, "foto": "https://s.glbimg.com/es/sde/f/2021/04/27/7b5d614f3eafc2e2e12922930cd3590e_FORMATO.png", "media": 3.94, "pontos": 7.73, "pontuacao": 7.73, "posicao_id": 6, "preco": 9.99, "preco_anterior": 9.4, "rodada_id": 28, "scout": null, "variacao": 0.59}, {"apelido": "Luiz Otávio ", "atleta_id": 86863, "capitao": false, "clube_id": 265, "entrou_em_campo": true, "foto": "https://s.glbimg.com/es/sde/f/2021/03/26/0e2a57894c04137ce7e329cbe588f1c2_FORMATO.png", "media": 2.92, "pontos": 13.8, "pontuacao": 13.8, "posicao_id": 3, "preco": 6.89, "preco_anterior": 5.2299999999999995, "rodada_id": 28, "scout": {"DS": 1, "G": 1, "PI": 2, "SG": 1}, "variacao": 1.66}, {"apelido": "Éder", "atleta_id": 91203, "capitao": false, "clube_id": 373, "entrou_em_campo": true, "foto": "https://s.glbimg.com/es/sde/f/2021/05/02/0302eafbbfe7b451db5ddf34a1c4bfaf_FORMATO.png", "media": 1.88, "pontos": 10.5, "pontuacao": 10.5, "posicao_id": 3, "preco": 9.07, "preco_anterior": 7.5200000000000005, "rodada_id": 28, "scout": {"A": 1, "FC": 1, "FF": 1, "FS": 1, "PI": 3, "SG": 1}, "variacao": 1.55}], "pontuacao": 175.83, "preco": 92.28000000000002, "valorizacao": 20.95}, {"esquema": {"esquema_id": 6, "nome": "5-3-2", "posicoes": {"ata": 2, "gol": 1, "lat": 2, "mei": 3, "tec": 1, "zag": 3}}, "jogadores": [{"apelido": "Sorriso", "atleta_id": 111333, "capitao": true, "clube_id": 286, "entrou_em_campo": true, "foto": "https://s.glbimg.com/es/sde/f/2021/03/25/5f6996b15f5e77bade868f8e343a077f_FORMATO.png", "media": 2.99, "pontos": 17.3, "pontuacao": 17.3, "posicao_id": 5, "preco": 7.36, "preco_anterior": 6.01, "rodada_id": 28, "scout": {"DS": 5, "FC": 1, "FD": 5, "FF": 4, "FS": 8, "PI": 4}, "variacao": 1.35}, {"apelido": "John Kennedy", "atleta_id": 110759, "capitao": false, "clube_id": 266, "entrou_em_campo": true, "foto": "https://s.glbimg.com/es/sde/f/2021/08/19/b1b9b8fc3e7ba9cdea447bad10b25ded_FORMATO.png", "media": 2.29, "pontos": 15.6, "pontuacao": 15.6, "posicao_id": 5, "preco": 5.47, "preco_anterior": 2.7399999999999998, "rodada_id": 28, "scout": {"CA": 1, "DS": 2, "FC": 3, "FD": 1, "FS": 2, "G": 2, "I": 1, "PI": 6}, "variacao": 2.73}, {"apelido": "Maílson", "atleta_id": 98034, "capitao": false, "clube_id": 292, "entrou_em_campo": true, "foto": "https://s.glbimg.com/es/sde/f/2021/04/27/978af8903185f1406809c274d6c681f5_FORMATO.png", "media": 5.09, "pontos": 12.5, "pontuacao": 12.5, "posicao_id": 1, "preco": 10.3, "preco_anterior": 9.270000000000001, "rodada_id": 28, "scout": {"DE": 14, "FS": 1, "GS": 2}, "variacao": 1.03}, {"apelido": "Igor Cariús", "atleta_id": 91639, "capitao": false, "clube_id": 373, "entrou_em_campo": true, "foto": "https://s.glbimg.com/es/sde/f/2021/03/11/e8078fb6e85f647acc4496fbee1d8b18_FORMATO.png", "media": 4.6, "pontos": 17.1, "pontuacao": 17.1, "posicao_id": 2, "preco": 13.61, "preco_anterior": 10.91, "rodada_id": 28, "scout": {"DS": 6, "FC": 3, "FS": 1, "G": 1, "PI": 9, "SG": 1}, "variacao": 2.7}, {"apelido": "Matheus Bahia", "atleta_id": 97899, "capitao": false, "clube_id": 265, "entrou_em_campo": true, "foto": "https://s.glbimg.com/es/sde/f/2021/04/19/52f1b5df1a1d88d986e939213804c1d0_FORMATO.png", "media": 4.98, "pontos": 12.1, "pontuacao": 12.1, "posicao_id": 2, "preco": 12.41, "preco_anterior": 11.33, "rodada_id": 28, "scout": {"A": 1, "DS": 2, "FC": 1, "FF": 1, "FS": 1, "PI": 7, "SG": 1}, "variacao": 1.08}, {"apelido": "Lucas Lima", "atleta_id": 80583, "capitao": false, "clube_id": 356, "entrou_em_campo": true, "foto": "https://s.glbimg.com/es/sde/f/2021/08/30/940ccef3e9a32ebab051e4e097fc4ec3_FORMATO.png", "media": 1.87, "pontos": 16.1, "pontuacao": 16.1, "posicao_id": 4, "preco": 6.35, "preco_anterior": 3.6799999999999997, "rodada_id": 28, "scout": {"A": 1, "DS": 1, "FC": 1, "FD": 1, "FF": 3, "G": 1, "PI": 10}, "variacao": 2.67}, {"apelido": "Alê", "atleta_id": 86388, "capitao": false, "clube_id": 327, "entrou_em_campo": true, "foto": "https://s.glbimg.com/es/sde/f/2021/06/04/fb4e69d36e6a93b5e9f5c927e3d29f8c_FORMATO.png", "media": 3.21, "pontos": 14.3, "pontuacao": 14.3, "posicao_id": 4, "preco": 7.17, "preco_anterior": 5.15, "rodada_id": 28, "scout": {"DS": 7, "FC": 2, "FS": 1, "G": 1, "PI": 2}, "variacao": 2.02}, {"apelido": "Gustavo Scarpa", "atleta_id": 87999, "capitao": false, "clube_id": 275, "entrou_em_campo": true, "foto": "https://s.glbimg.com/es/sde/f/2021/04/30/e594285e6781941b0f08b58d66d6669e_FORMATO.png", "media": 4.56, "pontos": 13.5, "pontuacao": 13.5, "posicao_id": 4, "preco": 14.84, "preco_anterior": 12.71, "rodada_id": 28, "scout": {"A": 1, "DS": 2, "FD": 3, "FF": 3, "FS": 3, "PI": 10}, "variacao": 2.13}, {"apelido": "Guto Ferreira", "atleta_id": 37245, "capitao": false, "clube_id": 265, "entrou_em_campo": true, "foto": "https://s.glbimg.com/es/sde/f/2021/04/27/7b5d614f3eafc2e2e12922930cd3590e_FORMATO.png", "media": 3.94, "pontos": 7.73, "pontuacao": 7.73, "posicao_id": 6, "preco": 9.99, "preco_anterior": 9.4, "rodada_id": 28, "scout": null, "variacao": 0.59}, {"apelido": "Luiz Otávio ", "atleta_id": 86863, "capitao": false, "clube_id": 265, "entrou_em_campo": true, "foto": "https://s.glbimg.com/es/sde/f/2021/03/26/0e2a57894c04137ce7e329cbe588f1c2_FORMATO.png", "media": 2.92, "pontos": 13.8, "pontuacao": 13.8, "posicao_id": 3, "preco": 6.89, "preco_anterior": 5.2299999999999995, "rodada_id": 28, "scout": {"DS": 1, "G": 1, "PI": 2, "SG": 1}, "variacao": 1.66}, {"apelido": "Éder", "atleta_id": 91203, "capitao": false, "clube_id": 373, "entrou_em_campo": true, "foto": "https://s.glbimg.com/es/sde/f/2021/05/02/0302eafbbfe7b451db5ddf34a1c4bfaf_FORMATO.png", "media": 1.88, "pontos": 10.5, "pontuacao": 10.5, "posicao_id": 3, "preco": 9.07, "preco_anterior": 7.5200000000000005, "rodada_id": 28, "scout": {"A": 1, "FC": 1, "FF": 1, "FS": 1, "PI": 3, "SG": 1}, "variacao": 1.55}, {"apelido": "Titi", "atleta_id": 50353, "capitao": false, "clube_id": 356, "entrou_em_campo": true, "foto": "https://s.glbimg.com/es/sde/f/2021/04/27/f556d6eae390e4f92eed5cf6ec49c085_FORMATO.png", "media": 3.69, "pontos": 8.1, "pontuacao": 8.1, "posicao_id": 3, "preco": 10.05, "preco_anterior": 10.040000000000001, "rodada_id": 28, "scout": {"DS": 3, "FC": 1, "FS": 2, "PI": 4, "SG": 1}, "variacao": 0.01}], "pontuacao": 175.93, "preco": 93.99000000000001, "valorizacao": 19.520000000000003}, {"esquema": {"esquema_id": 7, "nome": "5-4-1", "posicoes": {"ata": 1, "gol": 1, "lat": 2, "mei": 4, "tec": 1, "zag": 3}}, "jogadores": [{"apelido": "Sorriso", "atleta_id": 111333, "capitao": true, "clube_id": 286, "entrou_em_campo": true, "foto": "https://s.glbimg.com/es/sde/f/2021/03/25/5f6996b15f5e77bade868f8e343a077f_FORMATO.png", "media": 2.99, "pontos": 17.3, "pontuacao": 17.3, "posicao_id": 5, "preco": 7.36, "preco_anterior": 6.01, "rodada_id": 28, "scout": {"DS": 5, "FC": 1, "FD": 5, "FF": 4, "FS": 8, "PI": 4}, "variacao": 1.35}, {"apelido": "Maílson", "atleta_id": 98034, "capitao": false, "clube_id": 292, "entrou_em_campo": true, "foto": "https://s.glbimg.com/es/sde/f/2021/04/27/978af8903185f1406809c274d6c681f5_FORMATO.png", "media": 5.09, "pontos": 12.5, "pontuacao": 12.5, "posicao_id": 1, "preco": 10.3, "preco_anterior": 9.270000000000001, "rodada_id": 28, "scout": {"DE": 14, "FS": 1, "GS": 2}, "variacao": 1.03}, {"apelido": "Igor Cariús", "atleta_id": 91639, "capitao": false, "clube_id": 373, "entrou_em_campo": true, "foto": "https://s.glbimg.com/es/sde/f/2021/03/11/e8078fb6e85f647acc4496fbee1d8b18_FORMATO.png", "media": 4.6, "pontos": 17.1, "pontuacao": 17.1, "posicao_id": 2, "preco": 13.61, "preco_anterior": 10.91, "rodada_id": 28, "scout": {"DS": 6, "FC": 3, "FS": 1, "G": 1, "PI": 9, "SG": 1}, "variacao": 2.7}, {"apelido": "Matheus Bahia", "atleta_id": 97899, "capitao": false, "clube_id": 265, "entrou_em_campo": true, "foto": "https://s.glbimg.com/es/sde/f/2021/04/19/52f1b5df1a1d88d986e939213804c1d0_FORMATO.png", "media": 4.98, "pontos": 12.1, "pontuacao": 12.1, "posicao_id": 2, "preco": 12.41, "preco_anterior": 11.33, "rodada_id": 28, "scout": {"A": 1, "DS": 2, "FC": 1, "FF": 1, "FS": 1, "PI": 7, "SG": 1}, "variacao": 1.08}, {"apelido": "Lucas Lima", "atleta_id": 80583, "capitao": false, "clube_id": 356, "entrou_em_campo": true, "foto": "https://s.glbimg.com/es/sde/f/2021/08/30/940ccef3e9a32ebab051e4e097fc4ec3_FORMATO.png", "media": 1.87, "pontos": 16.1, "pontuacao": 16.1, "posicao_id": 4, "preco": 6.35, "preco_anterior": 3.6799999999999997, "rodada_id": 28, "scout": {"A": 1, "DS": 1, "FC": 1, "FD": 1, "FF": 3, "G": 1, "PI": 10}, "variacao": 2.67}, {"apelido": "Alê", "atleta_id": 86388, "capitao": false, "clube_id": 327, "entrou_em_campo": true, "foto": "https://s.glbimg.com/es/sde/f/2021/06/04/fb4e69d36e6a93b5e9f5c927e3d29f8c_FORMATO.png", "media": 3.21, "pontos": 14.3, "pontuacao": 14.3, "posicao_id": 4, "preco": 7.17, "preco_anterior": 5.15, "rodada_id": 28, "scout": {"DS": 7, "FC": 2, "FS": 1, "G": 1, "PI": 2}, "variacao": 2.02}, {"apelido": "Gustavo Scarpa", "atleta_id": 87999, "capitao": false, "clube_id": 275, "entrou_em_campo": true, "foto": "https://s.glbimg.com/es/sde/f/2021/04/30/e594285e6781941b0f08b58d66d6669e_FORMATO.png", "media": 4.56, "pontos": 13.5, "pontuacao": 13.5, "posicao_id": 4, "preco": 14.84, "preco_anterior": 12.71, "rodada_id": 28, "scout": {"A": 1, "DS": 2, "FD": 3, "FF": 3, "FS": 3, "PI": 10}, "variacao": 2.13}, {"apelido": "Felipe Melo", "atleta_id": 38545, "capitao": false, "clube_id": 275, "entrou_em_campo": true, "foto": "https://s.glbimg.com/es/sde/f/2021/04/30/6eeb5a32e1114760b24bf4689330fb43_FORMATO.png", "media": 1.06, "pontos": 11.8, "pontuacao": 11.8, "posicao_id": 4, "preco": 6.36, "preco_anterior": 3.7700000000000005, "rodada_id": 28, "scout": {"DS": 3, "FC": 2, "FF": 2, "FS": 1, "G": 1, "PI": 3}, "variacao": 2.59}, {"apelido": "Guto Ferreira", "atleta_id": 37245, "capitao": false, "clube_id": 265, "entrou_em_campo": true, "foto": "https://s.glbimg.com/es/sde/f/2021/04/27/7b5d614f3eafc2e2e12922930cd3590e_FORMATO.png", "media": 3.94, "pontos": 7.73, "pontuacao": 7.73, "posicao_id": 6, "preco": 9.99, "preco_anterior": 9.4, "rodada_id": 28, "scout": null, "variacao": 0.59}, {"apelido": "Luiz Otávio ", "atleta_id": 86863, "capitao": false, "clube_id": 265, "entrou_em_campo": true, "foto": "https://s.glbimg.com/es/sde/f/2021/03/26/0e2a57894c04137ce7e329cbe588f1c2_FORMATO.png", "media": 2.92, "pontos": 13.8, "pontuacao": 13.8, "posicao_id": 3, "preco": 6.89, "preco_anterior": 5.2299999999999995, "rodada_id": 28, "scout": {"DS": 1, "G": 1, "PI": 2, "SG": 1}, "variacao": 1.66}, {"apelido": "Éder", "atleta_id": 91203, "capitao": false, "clube_id": 373, "entrou_em_campo": true, "foto": "https://s.glbimg.com/es/sde/f/2021/05/02/0302eafbbfe7b451db5ddf34a1c4bfaf_FORMATO.png", "media": 1.88, "pontos": 10.5, "pontuacao": 10.5, "posicao_id": 3, "preco": 9.07, "preco_anterior": 7.5200000000000005, "rodada_id": 28, "scout": {"A": 1, "FC": 1, "FF": 1, "FS": 1, "PI": 3, "SG": 1}, "variacao": 1.55}, {"apelido": "Titi", "atleta_id": 50353, "capitao": false, "clube_id": 356, "entrou_em_campo": true, "foto": "https://s.glbimg.com/es/sde/f/2021/04/27/f556d6eae390e4f92eed5cf6ec49c085_FORMATO.png", "media": 3.69, "pontos": 8.1, "pontuacao": 8.1, "posicao_id": 3, "preco": 10.05, "preco_anterior": 10.040000000000001, "rodada_id": 28, "scout": {"DS": 3, "FC": 1, "FS": 2, "PI": 4, "SG": 1}, "variacao": 0.01}], "pontuacao": 172.13000000000002, "preco": 95.02000000000001, "valorizacao": 19.380000000000003}]